idem_vmware_alb/__init__.py
idem_vmware_alb/conf.py
idem_vmware_alb/version.py
idem_vmware_alb/acct/avilb/basic_auth.py
idem_vmware_alb/cloudspec/customize/avilb.py
idem_vmware_alb/exec/avilb/init.py
idem_vmware_alb/exec/avilb/applications/pool.py
idem_vmware_alb/exec/avilb/applications/virtual_service.py
idem_vmware_alb/exec/avilb/applications/vs_vip.py
idem_vmware_alb/exec/avilb/infrastructure/cloud.py
idem_vmware_alb/exec/avilb/infrastructure/service_engine_group.py
idem_vmware_alb/exec/avilb/profiles/application_persistence_profile.py
idem_vmware_alb/exec/avilb/profiles/application_profile.py
idem_vmware_alb/exec/avilb/profiles/health_monitor.py
idem_vmware_alb/exec/avilb/profiles/network_profile.py
idem_vmware_alb/exec/avilb/security/ssl_profile.py
idem_vmware_alb/states/avilb/init.py
idem_vmware_alb/states/avilb/applications/pool.py
idem_vmware_alb/states/avilb/applications/virtual_service.py
idem_vmware_alb/states/avilb/applications/vs_vip.py
idem_vmware_alb/states/avilb/infrastructure/cloud.py
idem_vmware_alb/states/avilb/infrastructure/service_engine_group.py
idem_vmware_alb/states/avilb/profiles/application_persistence_profile.py
idem_vmware_alb/states/avilb/profiles/application_profile.py
idem_vmware_alb/states/avilb/profiles/health_monitor.py
idem_vmware_alb/states/avilb/profiles/network_profile.py
idem_vmware_alb/states/avilb/security/ssl_profile.py
idem_vmware_alb/tool/avilb/apisession.py
idem_vmware_alb/tool/avilb/session.py
idem_vmware_alb/tool/avilb/test_state_utils.py
idem_vmware_alb/tool/avilb/utils.py
idem_vmware_alb-0.9.3.dist-info/LICENSE
idem_vmware_alb-0.9.3.dist-info/METADATA
idem_vmware_alb-0.9.3.dist-info/WHEEL
idem_vmware_alb-0.9.3.dist-info/top_level.txt
idem_vmware_alb-0.9.3.dist-info/RECORD
