Metadata-Version: 2.1
Name: idem-vmware-alb
Version: 0.9.3
Summary: VMware ALB Provider for Idem
Home-page: https://gitlab.com/vmware/idem/idem-vmware-alb
Author: VMware, Inc.
Author-email: idemproject@vmware.com
License: Apache Software License 2.0
Project-URL: Code, https://gitlab.com/vmware/idem/idem-vmware-alb
Project-URL: Issue tracker, https://gitlab.com/vmware/idem/idem-vmware-alb/-/issues
Classifier: Environment :: Console
Classifier: Intended Audience :: Developers
Classifier: Intended Audience :: Information Technology
Classifier: Intended Audience :: System Administrators
Classifier: Operating System :: OS Independent
Classifier: Programming Language :: Python
Classifier: Programming Language :: Python :: 3.8
Classifier: Programming Language :: Python :: 3.9
Classifier: Programming Language :: Python :: 3.10
Classifier: Programming Language :: Python :: 3.11
Classifier: Development Status :: 5 - Production/Stable
Classifier: License :: OSI Approved :: Apache Software License
Requires-Python: >=3.8
License-File: LICENSE
Requires-Dist: idem >=21.1.0
Requires-Dist: idem-aiohttp >=1.0.3
Requires-Dist: pop >=20.1.1
Requires-Dist: dict-toolbox >=2.1.2
Requires-Dist: aiohttp ==3.8.4
